[{"storeId": "ChIJiRmm2gemBY8RfLQlVw44GGc", "store": "GACAR", "openShiftPerWeek": 8, "schedule": [{"monday": [1, 1], "tuesday": [1, 0], "wednesday": [1, 1], "thursday": [0, 1], "friday": [1, 1]}]}, {"storeId": "ChIJ6cLpdAimBY8RLQWm0QoMloM", "store": "Aeropuerto Internacional Gustavo Rojas Pinilla", "openShiftPerWeek": 0, "schedule": [{"monday": [0, 0], "tuesday": [0, 0], "wednesday": [0, 0], "thursday": [0, 0], "friday": [0, 0]}]}, {"storeId": "ChIJ-Q55TAimBY8RWByl6GkUcHA", "store": "Flughafen San Andres Island", "openShiftPerWeek": 4, "schedule": [{"monday": [0, 0], "tuesday": [0, 0], "wednesday": [0, 1], "thursday": [1, 1], "friday": [0, 1]}]}, {"storeId": "ChIJf_0xkf-lBY8Rk1bQAuXFMsU", "store": "Cajero ATH San Andres I - Banco de Bogot\u00e1", "openShiftPerWeek": 3, "schedule": [{"monday": [1, 0], "tuesday": [0, 0], "wednesday": [0, 1], "thursday": [0, 0], "friday": [1, 0]}]}, {"storeId": "ChIJm-GGuhClBY8Rtio54OSwfSM", "store": "Bancolombia Corresponsal Bancario", "openShiftPerWeek": 6, "schedule": [{"monday": [1, 0], "tuesday": [1, 1], "wednesday": [0, 1], "thursday": [0, 1], "friday": [1, 0]}]}, {"storeId": "ChIJ7-cRMP6lBY8RCwj4VdIhpus", "store": "Servibanca", "openShiftPerWeek": 4, "schedule": [{"monday": [0, 0], "tuesday": [0, 1], "wednesday": [1, 0], "thursday": [0, 1], "friday": [0, 1]}]}, {"storeId": "ChIJ601PewCmBY8R64DxJ5bnHdM", "store": "Navitel - Internet", "openShiftPerWeek": 8, "schedule": [{"monday": [1, 1], "tuesday": [1, 1], "wednesday": [1, 1], "thursday": [1, 0], "friday": [0, 1]}]}, {"storeId": "ChIJgy2x4f-lBY8RGLcNfVHqWqk", "store": "Cajero ATH - Banco AV Villas", "openShiftPerWeek": 3, "schedule": [{"monday": [0, 0], "tuesday": [0, 1], "wednesday": [0, 1], "thursday": [0, 0], "friday": [0, 1]}]}, {"storeId": "ChIJJ9lNDP6lBY8RUNVqIzUgnOQ", "store": "Cajero ATH Oficina ProVIdencia I - Banco de Bogot\u00e1", "openShiftPerWeek": 2, "schedule": [{"monday": [0, 1], "tuesday": [0, 0], "wednesday": [0, 0], "thursday": [0, 0], "friday": [1, 0]}]}, {"storeId": "ChIJq-RpClSlBY8Rhl-Vvd6TDbA", "store": "Cajero Autom\u00e1tico Banco de Bogot\u00e1", "openShiftPerWeek": 4, "schedule": [{"monday": [1, 0], "tuesday": [0, 1], "wednesday": [0, 1], "thursday": [0, 1], "friday": [0, 0]}]}, {"storeId": "ChIJn0KYdQimBY8RSCHehLsy-sE", "store": "BBVA Cajero Aeropuerto San Andres", "openShiftPerWeek": 5, "schedule": [{"monday": [0, 1], "tuesday": [0, 0], "wednesday": [1, 0], "thursday": [1, 0], "friday": [1, 1]}]}, {"storeId": "ChIJQX0wEaCnBY8ROIJaOuC_CBo", "store": "Cajero Autom\u00e1tico Banco de Bogot\u00e1", "openShiftPerWeek": 3, "schedule": [{"monday": [1, 0], "tuesday": [1, 0], "wednesday": [0, 0], "thursday": [0, 0], "friday": [1, 0]}]}, {"storeId": "ChIJn6g5YwCmBY8RT2hBsL26dPU", "store": "La Helader\u00eda", "openShiftPerWeek": 6, "schedule": [{"monday": [0, 1], "tuesday": [1, 0], "wednesday": [1, 0], "thursday": [1, 1], "friday": [0, 1]}]}, {"storeId": "ChIJa-0tYf2lBY8ReODuQ3Yx6J8", "store": "Panaderia Do\u00f1a Ramona", "openShiftPerWeek": 2, "schedule": [{"monday": [0, 0], "tuesday": [0, 0], "wednesday": [0, 0], "thursday": [0, 1], "friday": [1, 0]}]}, {"storeId": "ChIJVU9hRv6lBY8RepztsIH4SSo", "store": "Banco Caja Social", "openShiftPerWeek": 7, "schedule": [{"monday": [1, 0], "tuesday": [0, 0], "wednesday": [1, 1], "thursday": [1, 1], "friday": [1, 1]}]}, {"storeId": "ChIJ9dlutv-lBY8RJIcMwDxcOA4", "store": "Pagafacil San Andres Islas", "openShiftPerWeek": 5, "schedule": [{"monday": [1, 1], "tuesday": [0, 0], "wednesday": [0, 0], "thursday": [1, 1], "friday": [0, 1]}]}, {"storeId": "ChIJiTWb3P-lBY8RaA5JZ0Uidig", "store": "Bank of Bogota", "openShiftPerWeek": 1, "schedule": [{"monday": [0, 0], "tuesday": [1, 0], "wednesday": [0, 0], "thursday": [0, 0], "friday": [0, 0]}]}, {"storeId": "ChIJebvMy_-lBY8RAlRmj4ABMzU", "store": "BANCOLOMBIA SAN ANDRES", "openShiftPerWeek": 5, "schedule": [{"monday": [1, 1], "tuesday": [1, 0], "wednesday": [0, 0], "thursday": [1, 0], "friday": [0, 1]}]}, {"storeId": "ChIJj4FCsv-lBY8R_0FagPoHB7Y", "store": "Banco de Occidente", "openShiftPerWeek": 7, "schedule": [{"monday": [1, 1], "tuesday": [0, 1], "wednesday": [1, 0], "thursday": [1, 1], "friday": [0, 1]}]}, {"storeId": "ChIJVarHOv6lBY8Rw02c-79tMEw", "store": "Banco agrario de colombia", "openShiftPerWeek": 4, "schedule": [{"monday": [1, 0], "tuesday": [1, 0], "wednesday": [0, 0], "thursday": [1, 0], "friday": [0, 1]}]}, {"storeId": "ChIJo0v1NP6lBY8RZ6YDho_AbsM", "store": "Banco Av Villas", "openShiftPerWeek": 0, "schedule": [{"monday": [0, 0], "tuesday": [0, 0], "wednesday": [0, 0], "thursday": [0, 0], "friday": [0, 0]}]}, {"storeId": "ChIJkfeR7B6lBY8RDnDfD637LkI", "store": "Cajero Banco de Occidente Red Aval", "openShiftPerWeek": 2, "schedule": [{"monday": [0, 0], "tuesday": [1, 0], "wednesday": [1, 0], "thursday": [0, 0], "friday": [0, 0]}]}, {"storeId": "ChIJw_dFuIWlBY8RnrG6GF8TUro", "store": "paga facil bancolombia", "openShiftPerWeek": 1, "schedule": [{"monday": [0, 0], "tuesday": [0, 0], "wednesday": [0, 0], "thursday": [0, 0], "friday": [1, 0]}]}, {"storeId": "ChIJqd_53f-lBY8Rmq7oUKPGrPo", "store": "Banco Davivienda", "openShiftPerWeek": 6, "schedule": [{"monday": [0, 0], "tuesday": [0, 1], "wednesday": [1, 0], "thursday": [1, 1], "friday": [1, 1]}]}, {"storeId": "ChIJO_w-s_-lBY8RwlUs7-f9E-Y", "store": "Banco Popular", "openShiftPerWeek": 2, "schedule": [{"monday": [0, 1], "tuesday": [0, 0], "wednesday": [0, 0], "thursday": [0, 1], "friday": [0, 0]}]}, {"storeId": "ChIJWd-JwK-lBY8Rcbd5NK3NY6w", "store": "Banco Popular", "openShiftPerWeek": 4, "schedule": [{"monday": [0, 0], "tuesday": [1, 0], "wednesday": [1, 0], "thursday": [1, 0], "friday": [1, 0]}]}, {"storeId": "ChIJPyJffnqlBY8R1hOE-svHhb0", "store": "Cajero Autom\u00e1tico Banco AV Villas", "openShiftPerWeek": 3, "schedule": [{"monday": [1, 0], "tuesday": [0, 0], "wednesday": [0, 0], "thursday": [1, 0], "friday": [0, 1]}]}, {"storeId": "ChIJYX2uTOSlBY8RXIP_lNGA4xo", "store": "Cajero Autom\u00e1tico Red Aval", "openShiftPerWeek": 4, "schedule": [{"monday": [0, 1], "tuesday": [1, 0], "wednesday": [0, 0], "thursday": [0, 1], "friday": [1, 0]}]}, {"storeId": "ChIJ8TWPSv6lBY8RSyJuA2A9Lts", "store": "Banco Av", "openShiftPerWeek": 2, "schedule": [{"monday": [0, 0], "tuesday": [0, 1], "wednesday": [1, 0], "thursday": [0, 0], "friday": [0, 0]}]}, {"storeId": "ChIJK3KSutalBY8RYJ0d2gSUGgo", "store": "Cajero Autom\u00e1tico Banco Caja Social", "openShiftPerWeek": 7, "schedule": [{"monday": [1, 1], "tuesday": [0, 1], "wednesday": [1, 1], "thursday": [0, 1], "friday": [1, 0]}]}, {"storeId": "ChIJ_-raRf6lBY8R2Kf3pyjDxjk", "store": "Cajero ath", "openShiftPerWeek": 2, "schedule": [{"monday": [0, 0], "tuesday": [0, 1], "wednesday": [1, 0], "thursday": [0, 0], "friday": [0, 0]}]}, {"storeId": "ChIJR9AvO_6lBY8R__jFSgIQC7g", "store": "Banagrario", "openShiftPerWeek": 4, "schedule": [{"monday": [0, 0], "tuesday": [0, 0], "wednesday": [0, 1], "thursday": [1, 0], "friday": [1, 1]}]}, {"storeId": "ChIJZ9qpdFinBY8RmRc6W7jbXGg", "store": "Banco de Bogot\u00e1", "openShiftPerWeek": 4, "schedule": [{"monday": [0, 1], "tuesday": [0, 1], "wednesday": [1, 0], "thursday": [1, 0], "friday": [0, 0]}]}, {"storeId": "ChIJV3akTWqlBY8RRPbBjF_cd_U", "store": "Banco caja social", "openShiftPerWeek": 5, "schedule": [{"monday": [0, 0], "tuesday": [1, 1], "wednesday": [1, 0], "thursday": [0, 1], "friday": [1, 0]}]}, {"storeId": "ChIJKzYEW0qlBY8Rks87lMqC7bk", "store": "Cajero Autom\u00e1tico Red Aval", "openShiftPerWeek": 3, "schedule": [{"monday": [0, 0], "tuesday": [1, 0], "wednesday": [0, 0], "thursday": [1, 0], "friday": [0, 1]}]}, {"storeId": "ChIJ9b_AnESlBY8R3y1sSUPvuH4", "store": "Cajero autom\u00e1tico bancolombia", "openShiftPerWeek": 4, "schedule": [{"monday": [0, 0], "tuesday": [1, 0], "wednesday": [0, 0], "thursday": [0, 1], "friday": [1, 1]}]}, {"storeId": "ChIJx7gt1V6lBY8R9wNmAJ3l9v4", "store": "Banco Popular", "openShiftPerWeek": 1, "schedule": [{"monday": [0, 0], "tuesday": [0, 0], "wednesday": [0, 0], "thursday": [0, 0], "friday": [0, 1]}]}, {"storeId": "ChIJz55WdlKlBY8RLRssgEW5Hys", "store": "Cajero Autom\u00e1tico Red Aval", "openShiftPerWeek": 1, "schedule": [{"monday": [0, 0], "tuesday": [0, 0], "wednesday": [0, 0], "thursday": [0, 0], "friday": [0, 1]}]}, {"storeId": "ChIJ2x5-1gunBY8REpZueWPPxEE", "store": "Cajero Autom\u00e1tico Red Aval", "openShiftPerWeek": 3, "schedule": [{"monday": [0, 0], "tuesday": [0, 0], "wednesday": [1, 0], "thursday": [1, 0], "friday": [0, 1]}]}, {"storeId": "ChIJH18_Jf6lBY8RvnUBuDmeMqU", "store": "Beauty Hair Peluqueria Y Spa", "openShiftPerWeek": 5, "schedule": [{"monday": [0, 0], "tuesday": [0, 1], "wednesday": [1, 0], "thursday": [1, 1], "friday": [0, 1]}]}, {"storeId": "ChIJy8sKIv6lBY8REvWBSxTasLY", "store": "Perfumera Fairuz", "openShiftPerWeek": 4, "schedule": [{"monday": [0, 1], "tuesday": [0, 0], "wednesday": [1, 0], "thursday": [0, 1], "friday": [1, 0]}]}, {"storeId": "ChIJF2nbuwCmBY8R8vTXRPTIYSM", "store": "Antojos Peluquera", "openShiftPerWeek": 5, "schedule": [{"monday": [0, 1], "tuesday": [1, 0], "wednesday": [0, 0], "thursday": [1, 1], "friday": [0, 1]}]}, {"storeId": "ChIJy483VdylBY8Rn-0_ZH34U-c", "store": "Arco Iris Regalos De Bendici\u00f3n", "openShiftPerWeek": 2, "schedule": [{"monday": [0, 1], "tuesday": [0, 0], "wednesday": [0, 0], "thursday": [0, 0], "friday": [0, 1]}]}, {"storeId": "ChIJDVHIlf-lBY8RSmXu2CRdpPI", "store": "Juan Valdez San Andr\u00e9s", "openShiftPerWeek": 3, "schedule": [{"monday": [0, 0], "tuesday": [1, 0], "wednesday": [0, 0], "thursday": [0, 0], "friday": [1, 1]}]}, {"storeId": "ChIJ-fEW0d6lBY8Ro-K2GWr0J-4", "store": "Caf\u00e9 Central", "openShiftPerWeek": 5, "schedule": [{"monday": [0, 0], "tuesday": [1, 1], "wednesday": [1, 0], "thursday": [1, 1], "friday": [0, 0]}]}, {"storeId": "ChIJPfKJxF-lBY8RWeVQ3tZ8N_E", "store": "Sugar momma original cakes", "openShiftPerWeek": 5, "schedule": [{"monday": [1, 0], "tuesday": [0, 0], "wednesday": [1, 1], "thursday": [1, 0], "friday": [0, 1]}]}, {"storeId": "ChIJn5bZC7inBY8RTSTDnfl913U", "store": "Macaya Mart\u00ednez", "openShiftPerWeek": 5, "schedule": [{"monday": [0, 0], "tuesday": [0, 0], "wednesday": [1, 1], "thursday": [1, 1], "friday": [0, 1]}]}, {"storeId": "ChIJ-wxkcv6lBY8RrJVp3jSGuNQ", "store": "Cafeteria de Julio y Anita", "openShiftPerWeek": 4, "schedule": [{"monday": [1, 0], "tuesday": [0, 0], "wednesday": [0, 1], "thursday": [0, 1], "friday": [0, 1]}]}, {"storeId": "ChIJV-BE9DWnBY8RbvtoNuthicY", "store": "Cafe Acuarius", "openShiftPerWeek": 4, "schedule": [{"monday": [0, 0], "tuesday": [0, 1], "wednesday": [0, 0], "thursday": [0, 1], "friday": [1, 1]}]}, {"storeId": "ChIJo2XljQCmBY8R9KvXOmvgJXM", "store": "NASA CARIBE", "openShiftPerWeek": 4, "schedule": [{"monday": [0, 0], "tuesday": [1, 0], "wednesday": [1, 1], "thursday": [1, 0], "friday": [0, 0]}]}, {"storeId": "ChIJH47zkoWnBY8R7lwms9qB5sk", "store": "Icelanda Coffee & Cream", "openShiftPerWeek": 0, "schedule": [{"monday": [0, 0], "tuesday": [0, 0], "wednesday": [0, 0], "thursday": [0, 0], "friday": [0, 0]}]}, {"storeId": "ChIJiyOGGv6lBY8Ri3JJObuLVEY", "store": "Zheng\u00b4s Coffe & Arts", "openShiftPerWeek": 5, "schedule": [{"monday": [0, 1], "tuesday": [1, 0], "wednesday": [0, 1], "thursday": [0, 1], "friday": [1, 0]}]}, {"storeId": "ChIJQe9OrzenBY8RMIoDfvrAzpU", "store": "Panaderia Y Cafeteria", "openShiftPerWeek": 6, "schedule": [{"monday": [0, 0], "tuesday": [1, 0], "wednesday": [1, 1], "thursday": [0, 1], "friday": [1, 1]}]}, {"storeId": "ChIJIdIi_v2lBY8RP9zCfuAULSQ", "store": "Celio\u2019s Coffee", "openShiftPerWeek": 2, "schedule": [{"monday": [1, 0], "tuesday": [0, 0], "wednesday": [0, 0], "thursday": [1, 0], "friday": [0, 0]}]}, {"storeId": "ChIJI0ES06anBY8RiMMTc5_b0v4", "store": "Caf\u00e9 Juan valdez", "openShiftPerWeek": 5, "schedule": [{"monday": [1, 1], "tuesday": [1, 1], "wednesday": [0, 1], "thursday": [0, 0], "friday": [0, 0]}]}, {"storeId": "ChIJG8Zy3wemBY8RZIZSBTYkRbQ", "store": "Caf\u00e9 OMA", "openShiftPerWeek": 5, "schedule": [{"monday": [1, 0], "tuesday": [0, 0], "wednesday": [1, 0], "thursday": [0, 1], "friday": [1, 1]}]}, {"storeId": "ChIJWz1W5gWmBY8RQKjcJ43EOzI", "store": "Panaderia y Reposteria Suzette", "openShiftPerWeek": 5, "schedule": [{"monday": [0, 1], "tuesday": [1, 0], "wednesday": [0, 0], "thursday": [1, 0], "friday": [1, 1]}]}, {"storeId": "ChIJe2QjZgemBY8RwKVJKZAOMMM", "store": "Rentacar Badavid", "openShiftPerWeek": 5, "schedule": [{"monday": [0, 1], "tuesday": [0, 0], "wednesday": [0, 1], "thursday": [1, 1], "friday": [1, 0]}]}, {"storeId": "ChIJm0wF_UClBY8RUO3YKw4Axks", "store": "Auteco Distribuidor de Repuestos Caribe Motos Rs Sas", "openShiftPerWeek": 2, "schedule": [{"monday": [0, 0], "tuesday": [1, 1], "wednesday": [0, 0], "thursday": [0, 0], "friday": [0, 0]}]}, {"storeId": "ChIJAVgtekGlBY8RaFHcAscIdqE", "store": "Auteco Centro de Servicio Autorizado Caribe Motos", "openShiftPerWeek": 6, "schedule": [{"monday": [0, 1], "tuesday": [0, 1], "wednesday": [1, 0], "thursday": [1, 1], "friday": [0, 1]}]}, {"storeId": "ChIJkfew1wmmBY8Rpsj-vZSifeU", "store": "Cementerio", "openShiftPerWeek": 5, "schedule": [{"monday": [0, 0], "tuesday": [0, 0], "wednesday": [1, 0], "thursday": [1, 1], "friday": [1, 1]}]}, {"storeId": "ChIJG68Sl-KlBY8RCjAxJ0ji-Fg", "store": "Iglesia de Dios Ministerial de Jesucristo Internacional - IDMJI - CGMJI San Andr", "openShiftPerWeek": 6, "schedule": [{"monday": [0, 1], "tuesday": [1, 1], "wednesday": [1, 0], "thursday": [0, 1], "friday": [0, 1]}]}, {"storeId": "ChIJH0kV6_2lBY8RRKhr5K6XWqk", "store": "Iglesia Cristiana Bautista", "openShiftPerWeek": 6, "schedule": [{"monday": [0, 1], "tuesday": [1, 1], "wednesday": [1, 0], "thursday": [0, 1], "friday": [1, 0]}]}, {"storeId": "ChIJ9x6mg66nBY8RTuWdlWHWU_0", "store": "Iglesia Mision Cristiana La Roca", "openShiftPerWeek": 4, "schedule": [{"monday": [1, 0], "tuesday": [1, 0], "wednesday": [1, 0], "thursday": [1, 0], "friday": [0, 0]}]}, {"storeId": "ChIJZcNEqxClBY8RvxLzpGk-G7w", "store": "Iglesia Bautista Monte de Sion", "openShiftPerWeek": 6, "schedule": [{"monday": [1, 0], "tuesday": [1, 1], "wednesday": [1, 0], "thursday": [0, 1], "friday": [0, 1]}]}, {"storeId": "ChIJLXRD3_ClBY8RjI6KaH-8-Mc", "store": "iglesia Jehov\u00e1 Tsidkenu del Cliff", "openShiftPerWeek": 6, "schedule": [{"monday": [1, 1], "tuesday": [1, 1], "wednesday": [1, 0], "thursday": [0, 0], "friday": [0, 1]}]}, {"storeId": "ChIJ3SCfTP6lBY8RuLRCrFQ7rwc", "store": "Perfumeria Beverly Hill 2", "openShiftPerWeek": 7, "schedule": [{"monday": [1, 0], "tuesday": [1, 1], "wednesday": [1, 0], "thursday": [0, 1], "friday": [1, 1]}]}, {"storeId": "ChIJ30O2Rf6lBY8RJzxVWRf4DWM", "store": "Miscelandia", "openShiftPerWeek": 3, "schedule": [{"monday": [0, 1], "tuesday": [1, 0], "wednesday": [0, 0], "thursday": [0, 0], "friday": [0, 1]}]}, {"storeId": "ChIJYe9hDf6lBY8RkGDLZKxMtxk", "store": "PATPRIMO SAN ANDRES", "openShiftPerWeek": 4, "schedule": [{"monday": [0, 0], "tuesday": [0, 0], "wednesday": [1, 1], "thursday": [0, 0], "friday": [1, 1]}]}, {"storeId": "ChIJYe9hDf6lBY8RbRITRw1diD8", "store": "PATPRIMO SAN ANDRES", "openShiftPerWeek": 2, "schedule": [{"monday": [0, 0], "tuesday": [1, 0], "wednesday": [0, 0], "thursday": [0, 0], "friday": [0, 1]}]}, {"storeId": "ChIJYe9hDf6lBY8ROSbjMYEuNys", "store": "PATPRIMO SAN ANDRES", "openShiftPerWeek": 3, "schedule": [{"monday": [1, 0], "tuesday": [0, 0], "wednesday": [0, 0], "thursday": [1, 1], "friday": [0, 0]}]}, {"storeId": "ChIJC3cLAf6lBY8R71bTf1aggew", "store": "Mattelsa San Andr\u00e9s - Tienda de Ropa", "openShiftPerWeek": 1, "schedule": [{"monday": [0, 0], "tuesday": [0, 0], "wednesday": [0, 0], "thursday": [0, 0], "friday": [0, 1]}]}, {"storeId": "ChIJF1492_-lBY8Rr2STE5hdtsE", "store": "Classic 2", "openShiftPerWeek": 5, "schedule": [{"monday": [1, 0], "tuesday": [0, 0], "wednesday": [0, 1], "thursday": [1, 1], "friday": [1, 0]}]}, {"storeId": "ChIJ589n_ZOlBY8RAm3SJaBfcgs", "store": "Almacen Junbar", "openShiftPerWeek": 1, "schedule": [{"monday": [0, 0], "tuesday": [0, 0], "wednesday": [0, 0], "thursday": [0, 0], "friday": [0, 1]}]}, {"storeId": "ChIJ6fNylv-lBY8RNqZHVEyp_NE", "store": "Vinotinto", "openShiftPerWeek": 5, "schedule": [{"monday": [1, 1], "tuesday": [1, 0], "wednesday": [0, 1], "thursday": [1, 0], "friday": [0, 0]}]}, {"storeId": "ChIJQ29MlP-lBY8RjNzfYvKITYw", "store": "United Colors of Benetton", "openShiftPerWeek": 6, "schedule": [{"monday": [0, 1], "tuesday": [0, 1], "wednesday": [1, 0], "thursday": [1, 1], "friday": [0, 1]}]}, {"storeId": "ChIJp6sHvv-lBY8RIKwcdYXMV3Q", "store": "Sport Wear", "openShiftPerWeek": 5, "schedule": [{"monday": [0, 1], "tuesday": [0, 0], "wednesday": [1, 1], "thursday": [0, 1], "friday": [0, 1]}]}, {"storeId": "ChIJZfdqwP-lBY8RYj4n0rUuG9E", "store": "Organza", "openShiftPerWeek": 6, "schedule": [{"monday": [0, 0], "tuesday": [1, 1], "wednesday": [1, 0], "thursday": [1, 1], "friday": [0, 1]}]}, {"storeId": "ChIJPwdU4oilBY8RdV7aOkKWNSs", "store": "AZULU", "openShiftPerWeek": 5, "schedule": [{"monday": [0, 1], "tuesday": [0, 1], "wednesday": [0, 1], "thursday": [1, 1], "friday": [0, 0]}]}, {"storeId": "ChIJtaFFuv-lBY8R_uO_bEbs2sk", "store": "Tienda La Riviera Duty Free", "openShiftPerWeek": 5, "schedule": [{"monday": [0, 0], "tuesday": [1, 1], "wednesday": [1, 1], "thursday": [0, 0], "friday": [0, 1]}]}, {"storeId": "ChIJP8x0wf-lBY8RQLrRnhZDlIo", "store": "Paris", "openShiftPerWeek": 4, "schedule": [{"monday": [1, 0], "tuesday": [0, 0], "wednesday": [1, 1], "thursday": [0, 1], "friday": [0, 0]}]}, {"storeId": "ChIJjRjxv_-lBY8RY-JIOD8zT7w", "store": "La Parfumerie", "openShiftPerWeek": 3, "schedule": [{"monday": [0, 1], "tuesday": [0, 1], "wednesday": [0, 0], "thursday": [1, 0], "friday": [0, 0]}]}, {"storeId": "ChIJl9tLsf-lBY8RohhuLPZuopg", "store": "Madrid Outlet", "openShiftPerWeek": 7, "schedule": [{"monday": [1, 0], "tuesday": [1, 0], "wednesday": [1, 0], "thursday": [1, 1], "friday": [1, 1]}]}, {"storeId": "ChIJrYpE2NSlBY8RyMJQu0mxIfM", "store": "LA FAMOSA DAVIVIENDA", "openShiftPerWeek": 7, "schedule": [{"monday": [0, 0], "tuesday": [1, 0], "wednesday": [1, 1], "thursday": [1, 1], "friday": [1, 1]}]}, {"storeId": "ChIJ45iB2_-lBY8RaIVXTfEispM", "store": "Kids Republic", "openShiftPerWeek": 2, "schedule": [{"monday": [0, 0], "tuesday": [0, 0], "wednesday": [0, 0], "thursday": [1, 0], "friday": [0, 1]}]}, {"storeId": "ChIJYzdGyv-lBY8RreAAnWdRRJ0", "store": "Brasili", "openShiftPerWeek": 7, "schedule": [{"monday": [1, 0], "tuesday": [1, 0], "wednesday": [1, 1], "thursday": [1, 0], "friday": [1, 1]}]}, {"storeId": "ChIJiVFf09KlBY8RXvf3uape718", "store": "Classic", "openShiftPerWeek": 2, "schedule": [{"monday": [1, 0], "tuesday": [0, 0], "wednesday": [0, 0], "thursday": [1, 0], "friday": [0, 0]}]}, {"storeId": "ChIJhflfGxWlBY8R3olv1Zq7Fvo", "store": "AZULU", "openShiftPerWeek": 1, "schedule": [{"monday": [0, 0], "tuesday": [0, 0], "wednesday": [0, 0], "thursday": [0, 0], "friday": [0, 1]}]}, {"storeId": "ChIJw738zP-lBY8RSHb6FHopsyo", "store": "Ropa Interior Gran Vida", "openShiftPerWeek": 3, "schedule": [{"monday": [1, 0], "tuesday": [0, 0], "wednesday": [0, 0], "thursday": [0, 1], "friday": [1, 0]}]}, {"storeId": "ChIJV1zuTP6lBY8ROTkif7WrbaM", "store": "Victoria Secret", "openShiftPerWeek": 2, "schedule": [{"monday": [0, 0], "tuesday": [0, 0], "wednesday": [0, 0], "thursday": [1, 0], "friday": [0, 1]}]}, {"storeId": "ChIJncdv2f-lBY8RtWBhD9Qd7UM", "store": "Kokai Kids", "openShiftPerWeek": 3, "schedule": [{"monday": [0, 0], "tuesday": [1, 0], "wednesday": [1, 0], "thursday": [0, 0], "friday": [1, 0]}]}, {"storeId": "ChIJAda3hgCmBY8RXS7LgWCZheo", "store": "Perfumer\u00eda Scada", "openShiftPerWeek": 3, "schedule": [{"monday": [0, 0], "tuesday": [0, 0], "wednesday": [0, 1], "thursday": [1, 0], "friday": [1, 0]}]}, {"storeId": "ChIJ7XVmNf6lBY8RjNPNpReTzGk", "store": "CW The Color Wear", "openShiftPerWeek": 6, "schedule": [{"monday": [1, 0], "tuesday": [1, 0], "wednesday": [0, 1], "thursday": [1, 0], "friday": [1, 1]}]}, {"storeId": "ChIJ-YypzP-lBY8RuGyg7rKlh6I", "store": "Fifa", "openShiftPerWeek": 5, "schedule": [{"monday": [0, 1], "tuesday": [1, 1], "wednesday": [0, 0], "thursday": [1, 0], "friday": [0, 1]}]}, {"storeId": "ChIJQaICzf-lBY8R1AJ1H-h1Wtg", "store": "Solario", "openShiftPerWeek": 5, "schedule": [{"monday": [0, 1], "tuesday": [1, 1], "wednesday": [0, 0], "thursday": [0, 1], "friday": [1, 0]}]}, {"storeId": "ChIJhc342P-lBY8RKfKmDWmeoNA", "store": "Micerino", "openShiftPerWeek": 1, "schedule": [{"monday": [0, 0], "tuesday": [0, 0], "wednesday": [0, 0], "thursday": [0, 0], "friday": [0, 1]}]}, {"storeId": "ChIJGQ9F2P-lBY8R_YfqINm9Bfs", "store": "Perfumeria Mil Aromas S.A.I.", "openShiftPerWeek": 1, "schedule": [{"monday": [0, 0], "tuesday": [0, 0], "wednesday": [0, 0], "thursday": [0, 0], "friday": [0, 1]}]}, {"storeId": "ChIJAx4V2P-lBY8RLrgpyGngl4E", "store": "Kamilos", "openShiftPerWeek": 5, "schedule": [{"monday": [0, 1], "tuesday": [0, 0], "wednesday": [0, 1], "thursday": [1, 1], "friday": [1, 0]}]}, {"storeId": "ChIJeVADMv6lBY8RNyqClRwdkpE", "store": "Al\u00eda Store", "openShiftPerWeek": 3, "schedule": [{"monday": [0, 0], "tuesday": [0, 1], "wednesday": [0, 1], "thursday": [1, 0], "friday": [0, 0]}]}, {"storeId": "ChIJMQyaeACmBY8RQDbv8u5PXJ8", "store": "Euro Moda", "openShiftPerWeek": 3, "schedule": [{"monday": [0, 1], "tuesday": [0, 0], "wednesday": [0, 0], "thursday": [1, 0], "friday": [1, 0]}]}, {"storeId": "ChIJ75hSFoKlBY8R9rEuvlxwpTQ", "store": "Almac\u00e9n Quitasue\u00f1o", "openShiftPerWeek": 4, "schedule": [{"monday": [1, 0], "tuesday": [0, 1], "wednesday": [0, 1], "thursday": [0, 1], "friday": [0, 0]}]}, {"storeId": "ChIJYf-WBz-lBY8R-iS7eDe87v4", "store": "PREVENCIONES INDUSTRIALES SAI", "openShiftPerWeek": 4, "schedule": [{"monday": [0, 0], "tuesday": [0, 1], "wednesday": [1, 0], "thursday": [1, 1], "friday": [0, 0]}]}, {"storeId": "ChIJOevtOP6lBY8RIwUhNbzAEhE", "store": "Almacen Exclusive", "openShiftPerWeek": 4, "schedule": [{"monday": [0, 0], "tuesday": [0, 1], "wednesday": [0, 0], "thursday": [1, 1], "friday": [1, 0]}]}, {"storeId": "ChIJpQb3voCnBY8R0t1780s5nJk", "store": "Variedades Izabel", "openShiftPerWeek": 5, "schedule": [{"monday": [1, 0], "tuesday": [0, 0], "wednesday": [0, 1], "thursday": [0, 1], "friday": [1, 1]}]}, {"storeId": "ChIJA40GSuylBY8RDRc1yNbOUjQ", "store": "Almacen Uni-2 - Inversiones Tesone Ltda.", "openShiftPerWeek": 8, "schedule": [{"monday": [0, 1], "tuesday": [0, 1], "wednesday": [1, 1], "thursday": [1, 1], "friday": [1, 1]}]}, {"storeId": "ChIJsdTG1P-lBY8Ro6DQ2YWeu80", "store": "Odontologo Alejandro Ibarra", "openShiftPerWeek": 6, "schedule": [{"monday": [0, 0], "tuesday": [0, 1], "wednesday": [1, 1], "thursday": [0, 1], "friday": [1, 1]}]}, {"storeId": "ChIJvwCE9gemBY8R9DqSZnyukLI", "store": "Servistar Construmundo", "openShiftPerWeek": 6, "schedule": [{"monday": [1, 0], "tuesday": [1, 1], "wednesday": [0, 1], "thursday": [1, 0], "friday": [0, 1]}]}, {"storeId": "ChIJGwbrTv6lBY8RP6y4SMI9ucE", "store": "El Vecino", "openShiftPerWeek": 7, "schedule": [{"monday": [1, 0], "tuesday": [1, 1], "wednesday": [1, 0], "thursday": [1, 1], "friday": [0, 1]}]}, {"storeId": "ChIJ6RKwk5KlBY8Rl9U_eupUGw4", "store": "Consultorio Pedi\u00e1trico Faraon Ospino", "openShiftPerWeek": 0, "schedule": [{"monday": [0, 0], "tuesday": [0, 0], "wednesday": [0, 0], "thursday": [0, 0], "friday": [0, 0]}]}, {"storeId": "ChIJq_bjtQCmBY8RP4ZUMdP7vf4", "store": "Restaurante Acuarius MiniMarket Drusgtore", "openShiftPerWeek": 10, "schedule": [{"monday": [1, 1], "tuesday": [1, 1], "wednesday": [1, 1], "thursday": [1, 1], "friday": [1, 1]}]}, {"storeId": "ChIJezFV-OilBY8RElUjBvfXjXQ", "store": "Servicio de Ingenier\u00eda El\u00e9ctrica SERINGEL S.A.S", "openShiftPerWeek": 6, "schedule": [{"monday": [1, 1], "tuesday": [1, 0], "wednesday": [1, 0], "thursday": [1, 1], "friday": [0, 0]}]}, {"storeId": "ChIJ22lKyGKlBY8RYjcFVoFujqM", "store": "Almacen Multiplaza", "openShiftPerWeek": 2, "schedule": [{"monday": [0, 1], "tuesday": [0, 0], "wednesday": [0, 0], "thursday": [0, 1], "friday": [0, 0]}]}, {"storeId": "ChIJRXmv83ylBY8Rtydo3ttqNpI", "store": "Aiwa", "openShiftPerWeek": 3, "schedule": [{"monday": [0, 1], "tuesday": [0, 0], "wednesday": [0, 1], "thursday": [1, 0], "friday": [0, 0]}]}, {"storeId": "ChIJ18qlzP-lBY8Rc3KC7sTGWQE", "store": "Sony Center", "openShiftPerWeek": 4, "schedule": [{"monday": [0, 1], "tuesday": [1, 1], "wednesday": [0, 1], "thursday": [0, 0], "friday": [0, 0]}]}, {"storeId": "ChIJm_Ht7KKlBY8RpjdzWAJiKkM", "store": "Games \"r\" us", "openShiftPerWeek": 3, "schedule": [{"monday": [0, 1], "tuesday": [0, 1], "wednesday": [0, 0], "thursday": [0, 0], "friday": [0, 1]}]}, {"storeId": "ChIJM4ZlF6ClBY8RP2RBanq1kz0", "store": "La Tienda Tech", "openShiftPerWeek": 5, "schedule": [{"monday": [1, 0], "tuesday": [0, 1], "wednesday": [1, 0], "thursday": [1, 1], "friday": [0, 0]}]}, {"storeId": "ChIJgTuJDiSlBY8RELXRluiBvxg", "store": "Almacen Multielectronic", "openShiftPerWeek": 0, "schedule": [{"monday": [0, 0], "tuesday": [0, 0], "wednesday": [0, 0], "thursday": [0, 0], "friday": [0, 0]}]}, {"storeId": "ChIJFYxua_6lBY8R1KsN2RwbLW4", "store": "Almac\u00e9n Jacobo", "openShiftPerWeek": 5, "schedule": [{"monday": [1, 1], "tuesday": [1, 0], "wednesday": [1, 0], "thursday": [0, 0], "friday": [1, 0]}]}, {"storeId": "ChIJn0Eq1v-lBY8Rf5WNiU5EJMA", "store": "almacen laila sai", "openShiftPerWeek": 2, "schedule": [{"monday": [0, 0], "tuesday": [1, 0], "wednesday": [0, 1], "thursday": [0, 0], "friday": [0, 0]}]}, {"storeId": "ChIJpVBZOP6lBY8R-BZ0TqplZzw", "store": "Tropicall Technology", "openShiftPerWeek": 3, "schedule": [{"monday": [1, 1], "tuesday": [0, 0], "wednesday": [0, 1], "thursday": [0, 0], "friday": [0, 0]}]}, {"storeId": "ChIJKSkyQf6lBY8RHa4sTzaWvXY", "store": "Multicenter Sony", "openShiftPerWeek": 2, "schedule": [{"monday": [0, 1], "tuesday": [0, 0], "wednesday": [1, 0], "thursday": [0, 0], "friday": [0, 0]}]}, {"storeId": "ChIJOyVXbfqlBY8RRKl51uzKg_c", "store": "HP STORE SEDE SAN ANDRES ISLAS", "openShiftPerWeek": 3, "schedule": [{"monday": [0, 1], "tuesday": [0, 0], "wednesday": [0, 1], "thursday": [0, 0], "friday": [1, 0]}]}, {"storeId": "ChIJFZMaGUelBY8RAwva-chL3dI", "store": "HP STORE", "openShiftPerWeek": 3, "schedule": [{"monday": [0, 1], "tuesday": [1, 0], "wednesday": [0, 0], "thursday": [0, 1], "friday": [0, 0]}]}, {"storeId": "ChIJ1ZhFQqunBY8RMS5gmzOwGTs", "store": "Almacen Multitechnic", "openShiftPerWeek": 5, "schedule": [{"monday": [0, 0], "tuesday": [0, 1], "wednesday": [1, 0], "thursday": [1, 0], "friday": [1, 1]}]}, {"storeId": "ChIJr84Mc_6lBY8RyFmZzjx0tQ4", "store": "Almacen Don Julio", "openShiftPerWeek": 0, "schedule": [{"monday": [0, 0], "tuesday": [0, 0], "wednesday": [0, 0], "thursday": [0, 0], "friday": [0, 0]}]}, {"storeId": "ChIJ72Lh5P2lBY8RoyyoH_Opz1c", "store": "Florister\u00eda Digalo Con Flores", "openShiftPerWeek": 4, "schedule": [{"monday": [1, 1], "tuesday": [1, 0], "wednesday": [0, 1], "thursday": [0, 0], "friday": [0, 0]}]}, {"storeId": "ChIJ6wKcIf6lBY8R6l_p6OegpAI", "store": "Casa Heno Daus", "openShiftPerWeek": 4, "schedule": [{"monday": [1, 0], "tuesday": [0, 0], "wednesday": [1, 0], "thursday": [1, 0], "friday": [0, 1]}]}, {"storeId": "ChIJ6WCG7v2lBY8RobVsdD7nMJ0", "store": "Muebleria Costa", "openShiftPerWeek": 6, "schedule": [{"monday": [1, 0], "tuesday": [1, 0], "wednesday": [0, 1], "thursday": [0, 1], "friday": [1, 1]}]}, {"storeId": "ChIJK33WWwemBY8Rm_KmW-xO8CE", "store": "Texaco", "openShiftPerWeek": 10, "schedule": [{"monday": [1, 1], "tuesday": [1, 1], "wednesday": [1, 1], "thursday": [1, 1], "friday": [1, 1]}]}, {"storeId": "ChIJm0EQyQemBY8RL-_SXg_Jubs", "store": "Planta Chevron Aviacion", "openShiftPerWeek": 10, "schedule": [{"monday": [1, 1], "tuesday": [1, 1], "wednesday": [1, 1], "thursday": [1, 1], "friday": [1, 1]}]}, {"storeId": "ChIJ68u8ewemBY8Rd2S-6YcsDos", "store": "Coliseo Rosado", "openShiftPerWeek": 5, "schedule": [{"monday": [0, 1], "tuesday": [0, 1], "wednesday": [0, 1], "thursday": [0, 1], "friday": [0, 1]}]}, {"storeId": "ChIJdeT2nvKnBY8Ru_nck7gqHVQ", "store": "Ina shape gym", "openShiftPerWeek": 4, "schedule": [{"monday": [0, 0], "tuesday": [0, 1], "wednesday": [0, 1], "thursday": [1, 1], "friday": [0, 0]}]}, {"storeId": "ChIJOxf3szilBY8RoWoDfmMRLz0", "store": "Antony\u00b4s Peluquer\u00eda", "openShiftPerWeek": 4, "schedule": [{"monday": [0, 1], "tuesday": [0, 0], "wednesday": [1, 0], "thursday": [1, 0], "friday": [0, 1]}]}, {"storeId": "ChIJlcbfmm6lBY8RHPaH8UCNJ8Q", "store": "BROTHER'S BARBER SHOP SAI", "openShiftPerWeek": 5, "schedule": [{"monday": [1, 0], "tuesday": [1, 0], "wednesday": [0, 1], "thursday": [0, 1], "friday": [0, 1]}]}, {"storeId": "ChIJVS2vrginBY8R8iuTW2MPdQ4", "store": "Maikey's VIP Barber Shop", "openShiftPerWeek": 5, "schedule": [{"monday": [0, 0], "tuesday": [0, 1], "wednesday": [0, 1], "thursday": [1, 1], "friday": [0, 1]}]}, {"storeId": "ChIJF4EPygGlBY8RN00h1SIQl1U", "store": "Ferreteria La Casa Del Pintor", "openShiftPerWeek": 5, "schedule": [{"monday": [0, 0], "tuesday": [1, 0], "wednesday": [1, 1], "thursday": [0, 0], "friday": [1, 1]}]}, {"storeId": "ChIJB2Myq_elBY8RB2hCBTBxx8I", "store": "Ferreter\u00eda Apolo", "openShiftPerWeek": 1, "schedule": [{"monday": [0, 0], "tuesday": [0, 0], "wednesday": [0, 0], "thursday": [0, 0], "friday": [0, 1]}]}, {"storeId": "ChIJ-wzGs_-lBY8RiZ1EOQ3fT_c", "store": "Classic Hogar", "openShiftPerWeek": 6, "schedule": [{"monday": [0, 0], "tuesday": [1, 1], "wednesday": [0, 1], "thursday": [1, 1], "friday": [0, 1]}]}, {"storeId": "ChIJJ6VW2_-lBY8RjoT4euBFCe8", "store": "Almacen Lalamoon", "openShiftPerWeek": 7, "schedule": [{"monday": [1, 1], "tuesday": [0, 1], "wednesday": [1, 1], "thursday": [0, 0], "friday": [1, 1]}]}, {"storeId": "ChIJ98TNz_-lBY8R8BPkHIBz5As", "store": "Perfumer\u00eda Beverly Hills 4", "openShiftPerWeek": 3, "schedule": [{"monday": [0, 1], "tuesday": [1, 0], "wednesday": [0, 0], "thursday": [0, 1], "friday": [0, 0]}]}, {"storeId": "ChIJc91eTP6lBY8RaxsNY_yTJ9Q", "store": "Benerly Hills", "openShiftPerWeek": 3, "schedule": [{"monday": [1, 0], "tuesday": [1, 0], "wednesday": [0, 0], "thursday": [0, 0], "friday": [1, 0]}]}, {"storeId": "ChIJuxbP_VqlBY8R0tPuqY2-HyA", "store": "5ta Avenida Tienda Lociones", "openShiftPerWeek": 4, "schedule": [{"monday": [0, 1], "tuesday": [1, 0], "wednesday": [0, 0], "thursday": [1, 1], "friday": [0, 0]}]}, {"storeId": "ChIJyetYhwCmBY8RW99qyA7AxS4", "store": "The Riviera Duty Free", "openShiftPerWeek": 3, "schedule": [{"monday": [0, 0], "tuesday": [1, 1], "wednesday": [0, 0], "thursday": [0, 0], "friday": [0, 1]}]}, {"storeId": "ChIJbXVUlJKlBY8RT9fTR0NCmjc", "store": "Dtodo3", "openShiftPerWeek": 4, "schedule": [{"monday": [1, 1], "tuesday": [0, 0], "wednesday": [0, 1], "thursday": [0, 0], "friday": [1, 0]}]}, {"storeId": "ChIJsxWya_6lBY8ROFWAYFX9zFk", "store": "El Hogar", "openShiftPerWeek": 4, "schedule": [{"monday": [1, 0], "tuesday": [0, 1], "wednesday": [0, 1], "thursday": [0, 0], "friday": [0, 1]}]}, {"storeId": "ChIJrf-0cRelBY8R9lbRdLloVLs", "store": "Super Jacky 2", "openShiftPerWeek": 1, "schedule": [{"monday": [0, 0], "tuesday": [0, 0], "wednesday": [0, 0], "thursday": [0, 0], "friday": [0, 1]}]}, {"storeId": "ChIJ_5RGPvylBY8RPzMqJy0jd7o", "store": "Decoraciones y Banquetes Lucia", "openShiftPerWeek": 4, "schedule": [{"monday": [0, 1], "tuesday": [0, 0], "wednesday": [1, 0], "thursday": [0, 1], "friday": [0, 1]}]}, {"storeId": "ChIJvyGkvQCmBY8RGvPS0wGVJxU", "store": "Superpopular Discount", "openShiftPerWeek": 3, "schedule": [{"monday": [1, 1], "tuesday": [0, 1], "wednesday": [0, 0], "thursday": [0, 0], "friday": [0, 0]}]}, {"storeId": "ChIJuZN_z4KlBY8RfzUlfOHjMrY", "store": "Representaciones Y Servicios JM", "openShiftPerWeek": 5, "schedule": [{"monday": [0, 1], "tuesday": [1, 0], "wednesday": [0, 0], "thursday": [1, 1], "friday": [0, 1]}]}, {"storeId": "ChIJ6feVrGalBY8RVNp2HL5gxK0", "store": "Mundo Seguros", "openShiftPerWeek": 4, "schedule": [{"monday": [1, 0], "tuesday": [0, 0], "wednesday": [1, 0], "thursday": [0, 0], "friday": [1, 1]}]}, {"storeId": "ChIJMWaM372nBY8ROio0mF8WMNc", "store": "Almacen Ranpi's", "openShiftPerWeek": 5, "schedule": [{"monday": [0, 1], "tuesday": [1, 0], "wednesday": [0, 0], "thursday": [0, 1], "friday": [1, 1]}]}, {"storeId": "ChIJrQZjGv6lBY8R0_kBjju45so", "store": "Esmeraldas Colombianas", "openShiftPerWeek": 0, "schedule": [{"monday": [0, 0], "tuesday": [0, 0], "wednesday": [0, 0], "thursday": [0, 0], "friday": [0, 0]}]}, {"storeId": "ChIJWdaLYnOlBY8Ry_bmcmQ77OM", "store": "Lavander\u00eda San Andr\u00e9s", "openShiftPerWeek": 7, "schedule": [{"monday": [1, 1], "tuesday": [0, 1], "wednesday": [0, 0], "thursday": [1, 1], "friday": [1, 1]}]}, {"storeId": "ChIJ_W4Qy_-lBY8R1Qyn-Fjdwl0", "store": "Biblioteca Banco De La Republica San Andres", "openShiftPerWeek": 2, "schedule": [{"monday": [0, 0], "tuesday": [0, 0], "wednesday": [1, 0], "thursday": [0, 0], "friday": [1, 0]}]}, {"storeId": "ChIJVUvS2v-lBY8RFhil4bRc1ho", "store": "Rancho Licores Drinks", "openShiftPerWeek": 2, "schedule": [{"monday": [0, 0], "tuesday": [0, 0], "wednesday": [0, 0], "thursday": [1, 1], "friday": [0, 0]}]}, {"storeId": "ChIJebMpdACmBY8Rmr0A8i1mbwQ", "store": "World House # 2", "openShiftPerWeek": 3, "schedule": [{"monday": [1, 0], "tuesday": [0, 0], "wednesday": [0, 0], "thursday": [0, 0], "friday": [1, 1]}]}, {"storeId": "ChIJXWRbGv6lBY8RJScs-Eq1rrM", "store": "PONCHOS PLACE BY DSL", "openShiftPerWeek": 5, "schedule": [{"monday": [0, 1], "tuesday": [0, 1], "wednesday": [0, 0], "thursday": [1, 1], "friday": [0, 1]}]}, {"storeId": "ChIJd--nvQCmBY8RXJPAwLqYddM", "store": "iA INTERNACIONAL SAS", "openShiftPerWeek": 4, "schedule": [{"monday": [0, 0], "tuesday": [1, 0], "wednesday": [0, 1], "thursday": [1, 0], "friday": [1, 0]}]}, {"storeId": "ChIJUW-fdQimBY8RJO_egt0zP0g", "store": "Aerodiscos", "openShiftPerWeek": 3, "schedule": [{"monday": [1, 0], "tuesday": [0, 1], "wednesday": [1, 0], "thursday": [0, 0], "friday": [0, 0]}]}, {"storeId": "ChIJU9gGcQCmBY8RpFCilTg5p0k", "store": "Jet Sky Rental", "openShiftPerWeek": 3, "schedule": [{"monday": [0, 0], "tuesday": [1, 0], "wednesday": [0, 0], "thursday": [1, 0], "friday": [0, 1]}]}, {"storeId": "ChIJwU9BOv6lBY8RU1VU0rEQdLE", "store": "Palacio de Justicia San Andr\u00e9s", "openShiftPerWeek": 3, "schedule": [{"monday": [0, 0], "tuesday": [0, 1], "wednesday": [0, 1], "thursday": [0, 0], "friday": [0, 1]}]}, {"storeId": "ChIJS5jsrV2nBY8RkxUyH-YWCJc", "store": "CFSM - SAN ANDR\u00c9S", "openShiftPerWeek": 6, "schedule": [{"monday": [1, 0], "tuesday": [1, 1], "wednesday": [1, 0], "thursday": [0, 1], "friday": [1, 0]}]}, {"storeId": "ChIJnysu61WvBY8Rbg7QttoSu1w", "store": "Hotel Casablanca", "openShiftPerWeek": 4, "schedule": [{"monday": [0, 0], "tuesday": [0, 1], "wednesday": [1, 1], "thursday": [0, 0], "friday": [0, 1]}]}, {"storeId": "ChIJrQaQEv6lBY8RD9-VFRdZJ_U", "store": "Hotel Las Am\u00e9ricas", "openShiftPerWeek": 6, "schedule": [{"monday": [0, 1], "tuesday": [0, 1], "wednesday": [1, 0], "thursday": [1, 1], "friday": [1, 0]}]}, {"storeId": "ChIJWb8-tQCmBY8RDBkR_a9uMwo", "store": "Hotel Portobelo Boulevard", "openShiftPerWeek": 6, "schedule": [{"monday": [1, 0], "tuesday": [0, 0], "wednesday": [1, 0], "thursday": [1, 1], "friday": [1, 1]}]}, {"storeId": "ChIJIZPbhv-lBY8RB83d69Z1O_s", "store": "Decameron Isle\u00f1o", "openShiftPerWeek": 3, "schedule": [{"monday": [1, 1], "tuesday": [0, 0], "wednesday": [0, 0], "thursday": [1, 0], "friday": [0, 0]}]}, {"storeId": "ChIJW40ZSwemBY8RW0nwJ8YKrPA", "store": "Hotel Portobelo Beach", "openShiftPerWeek": 2, "schedule": [{"monday": [0, 0], "tuesday": [1, 0], "wednesday": [0, 0], "thursday": [1, 0], "friday": [0, 0]}]}, {"storeId": "ChIJzZsLZEH8RI4RZ4KzQ1dsYLo", "store": "San Andr\u00e9s Noblehouse Hotel", "openShiftPerWeek": 2, "schedule": [{"monday": [1, 0], "tuesday": [0, 0], "wednesday": [0, 0], "thursday": [0, 0], "friday": [0, 1]}]}, {"storeId": "ChIJnUerta3_RI4RSZ5gS3-q8IQ", "store": "Hotel Bah\u00eda Sardina", "openShiftPerWeek": 7, "schedule": [{"monday": [1, 1], "tuesday": [0, 1], "wednesday": [1, 1], "thursday": [1, 1], "friday": [0, 0]}]}, {"storeId": "ChIJiyw2hwCmBY8R5dzxLVTyn-c", "store": "Apartahotel Limsor", "openShiftPerWeek": 2, "schedule": [{"monday": [0, 1], "tuesday": [0, 1], "wednesday": [0, 0], "thursday": [0, 0], "friday": [0, 0]}]}, {"storeId": "ChIJ4euVV-SlBY8RP_kriWPr1Ug", "store": "Maryland Decameron Resort", "openShiftPerWeek": 7, "schedule": [{"monday": [0, 0], "tuesday": [0, 1], "wednesday": [1, 1], "thursday": [1, 1], "friday": [1, 1]}]}, {"storeId": "ChIJwbc8fQCmBY8REawXKr4DQcA", "store": "Hotel Tiuna", "openShiftPerWeek": 5, "schedule": [{"monday": [1, 0], "tuesday": [0, 1], "wednesday": [0, 1], "thursday": [0, 0], "friday": [1, 1]}]}, {"storeId": "ChIJd0jc7P2lBY8RovkXwK8LnUo", "store": "Hotel Hernando Henry", "openShiftPerWeek": 8, "schedule": [{"monday": [1, 1], "tuesday": [1, 1], "wednesday": [0, 1], "thursday": [1, 1], "friday": [0, 1]}]}, {"storeId": "ChIJO-hSw_-lBY8RDt9GuIJP9mw", "store": "Hotel Blue Ton\u00e9", "openShiftPerWeek": 5, "schedule": [{"monday": [0, 1], "tuesday": [1, 0], "wednesday": [1, 0], "thursday": [1, 0], "friday": [1, 0]}]}, {"storeId": "ChIJxSK2vwCmBY8RF7VzDt1OVag", "store": "Sandwich Qbano", "openShiftPerWeek": 7, "schedule": [{"monday": [1, 0], "tuesday": [1, 1], "wednesday": [1, 1], "thursday": [1, 0], "friday": [0, 1]}]}, {"storeId": "ChIJ9TSoiQCmBY8RWodiz1igTJ0", "store": "Cinema Tiuna", "openShiftPerWeek": 3, "schedule": [{"monday": [0, 0], "tuesday": [0, 1], "wednesday": [0, 0], "thursday": [1, 1], "friday": [0, 0]}]}, {"storeId": "ChIJtxLzYgCmBY8R-hByepPujzE", "store": "Cine Bar El Faro", "openShiftPerWeek": 6, "schedule": [{"monday": [1, 1], "tuesday": [0, 0], "wednesday": [0, 1], "thursday": [0, 1], "friday": [1, 1]}]}, {"storeId": "ChIJ54f3ogCmBY8RbxOscFR8k6M", "store": "Teatro Hollywood", "openShiftPerWeek": 5, "schedule": [{"monday": [1, 1], "tuesday": [0, 0], "wednesday": [1, 1], "thursday": [0, 0], "friday": [1, 0]}]}, {"storeId": "ChIJncCdD3CnBY8Rk-pX53mvuV0", "store": "LATAM Cargo Dom\u00e9stico San Andr\u00e9s", "openShiftPerWeek": 4, "schedule": [{"monday": [0, 1], "tuesday": [0, 1], "wednesday": [0, 0], "thursday": [0, 1], "friday": [0, 1]}]}, {"storeId": "ChIJ31qoqU2nBY8RlPvI5N284Xk", "store": "Playa Para Caretear", "openShiftPerWeek": 3, "schedule": [{"monday": [0, 1], "tuesday": [0, 1], "wednesday": [0, 0], "thursday": [0, 0], "friday": [0, 1]}]}, {"storeId": "ChIJO7dYTwamBY8RlKM2j3eV6e0", "store": "San Andr\u00e9s Ecological Park", "openShiftPerWeek": 4, "schedule": [{"monday": [0, 1], "tuesday": [1, 0], "wednesday": [0, 0], "thursday": [0, 1], "friday": [0, 1]}]}, {"storeId": "ChIJyxWUBP6lBY8RDvHUbXeyid0", "store": "Parque Manawar", "openShiftPerWeek": 7, "schedule": [{"monday": [1, 0], "tuesday": [1, 1], "wednesday": [1, 1], "thursday": [0, 0], "friday": [1, 1]}]}, {"storeId": "ChIJXyZe9Q6nBY8RmfaK2_Jm70w", "store": "Banquitos del Aeropuerto", "openShiftPerWeek": 4, "schedule": [{"monday": [0, 0], "tuesday": [1, 0], "wednesday": [0, 0], "thursday": [1, 1], "friday": [0, 1]}]}, {"storeId": "ChIJESDGDgimBY8RDIgoRNbl-HQ", "store": "Parqueadero Aeropuerto", "openShiftPerWeek": 5, "schedule": [{"monday": [0, 1], "tuesday": [0, 0], "wednesday": [1, 1], "thursday": [0, 1], "friday": [0, 1]}]}, {"storeId": "ChIJ_UDsvQCmBY8R_V7b9bVuoLQ", "store": "Discount Drugs", "openShiftPerWeek": 10, "schedule": [{"monday": [1, 1], "tuesday": [1, 1], "wednesday": [1, 1], "thursday": [1, 1], "friday": [1, 1]}]}, {"storeId": "ChIJjztLuQCmBY8Rohys6ZzUw9U", "store": "Rebate Plus # 1 San Andres Islands Avenida 20 de Julio", "openShiftPerWeek": 10, "schedule": [{"monday": [1, 1], "tuesday": [1, 1], "wednesday": [1, 1], "thursday": [1, 1], "friday": [1, 1]}]}, {"storeId": "ChIJr1Gftv-lBY8RaZ7g6KbJbTg", "store": "Cruz Verde San Andr\u00e9s", "openShiftPerWeek": 10, "schedule": [{"monday": [1, 1], "tuesday": [1, 1], "wednesday": [1, 1], "thursday": [1, 1], "friday": [1, 1]}]}, {"storeId": "ChIJs-f62_-lBY8RDUHhlEooQEU", "store": "Droguera La Salud Islea", "openShiftPerWeek": 10, "schedule": [{"monday": [1, 1], "tuesday": [1, 1], "wednesday": [1, 1], "thursday": [1, 1], "friday": [1, 1]}]}, {"storeId": "ChIJSVXu2_-lBY8RacPawnVmGgo", "store": "The Isle\u00f1a Health Drugstore", "openShiftPerWeek": 10, "schedule": [{"monday": [1, 1], "tuesday": [1, 1], "wednesday": [1, 1], "thursday": [1, 1], "friday": [1, 1]}]}, {"storeId": "ChIJMZX75IWlBY8RPtfwjQqeLw8", "store": "Farmacenter El Socorro", "openShiftPerWeek": 10, "schedule": [{"monday": [1, 1], "tuesday": [1, 1], "wednesday": [1, 1], "thursday": [1, 1], "friday": [1, 1]}]}, {"storeId": "ChIJ3ZvYDf6lBY8RUCUtwvx9LAc", "store": "Servidrogas El Manantial", "openShiftPerWeek": 10, "schedule": [{"monday": [1, 1], "tuesday": [1, 1], "wednesday": [1, 1], "thursday": [1, 1], "friday": [1, 1]}]}, {"storeId": "ChIJqXyV8vOlBY8RebT2HSqLrj4", "store": "Farmacenter Manantial", "openShiftPerWeek": 10, "schedule": [{"monday": [1, 1], "tuesday": [1, 1], "wednesday": [1, 1], "thursday": [1, 1], "friday": [1, 1]}]}, {"storeId": "ChIJAcEidP6lBY8RXRPNBRGjQYI", "store": "Farmacenter Las Am\u00e9ricas", "openShiftPerWeek": 10, "schedule": [{"monday": [1, 1], "tuesday": [1, 1], "wednesday": [1, 1], "thursday": [1, 1], "friday": [1, 1]}]}, {"storeId": "ChIJZ8MN4_2lBY8RkmPxsX7hPMY", "store": "Farmacia Ruth", "openShiftPerWeek": 10, "schedule": [{"monday": [1, 1], "tuesday": [1, 1], "wednesday": [1, 1], "thursday": [1, 1], "friday": [1, 1]}]}, {"storeId": "ChIJD7L6VAemBY8Rc3zZ0QT9fTo", "store": "Ruth Droguer\u00eda No. 2", "openShiftPerWeek": 10, "schedule": [{"monday": [1, 1], "tuesday": [1, 1], "wednesday": [1, 1], "thursday": [1, 1], "friday": [1, 1]}]}, {"storeId": "ChIJ-3ewKmGlBY8RE3eN6apZQ0k", "store": "FARMACENTER RUTH 2", "openShiftPerWeek": 10, "schedule": [{"monday": [1, 1], "tuesday": [1, 1], "wednesday": [1, 1], "thursday": [1, 1], "friday": [1, 1]}]}, {"storeId": "ChIJ6a9Jsu-lBY8R17GoRVfq_Bo", "store": "REBAJA PLUS No. 2 SAN ANDRES ISLAS C. C. LA CASA DEL MAR", "openShiftPerWeek": 10, "schedule": [{"monday": [1, 1], "tuesday": [1, 1], "wednesday": [1, 1], "thursday": [1, 1], "friday": [1, 1]}]}, {"storeId": "ChIJb-kqsOKlBY8RjfGXZ4drxvU", "store": "GNF OXIGENO", "openShiftPerWeek": 10, "schedule": [{"monday": [1, 1], "tuesday": [1, 1], "wednesday": [1, 1], "thursday": [1, 1], "friday": [1, 1]}]}, {"storeId": "ChIJB9ue1vmnBY8R9yrAqZrBmAQ", "store": "Farmacenter Ruth 2", "openShiftPerWeek": 10, "schedule": [{"monday": [1, 1], "tuesday": [1, 1], "wednesday": [1, 1], "thursday": [1, 1], "friday": [1, 1]}]}, {"storeId": "ChIJrY1lW_2lBY8Re03N0jLs-U0", "store": "luna de verano - apartaestudios centro", "openShiftPerWeek": 6, "schedule": [{"monday": [0, 1], "tuesday": [1, 1], "wednesday": [0, 1], "thursday": [1, 1], "friday": [0, 0]}]}, {"storeId": "ChIJM-hHrwimBY8RzoZ6oXFEQzo", "store": "CASA HOSTEL SAN ANDRES", "openShiftPerWeek": 5, "schedule": [{"monday": [1, 1], "tuesday": [1, 0], "wednesday": [1, 0], "thursday": [0, 0], "friday": [0, 1]}]}, {"storeId": "ChIJAQvs_lynBY8RPie7-bWuisU", "store": "Su Casa Inmobiliaria del Caribe", "openShiftPerWeek": 2, "schedule": [{"monday": [0, 0], "tuesday": [0, 0], "wednesday": [0, 0], "thursday": [1, 0], "friday": [0, 1]}]}, {"storeId": "ChIJQbLkUQ-mBY8R0i4a8ijSbRk", "store": "Hostal Solymarislas", "openShiftPerWeek": 3, "schedule": [{"monday": [0, 0], "tuesday": [0, 0], "wednesday": [1, 1], "thursday": [0, 1], "friday": [0, 0]}]}, {"storeId": "ChIJUbhbSQemBY8RbumWXEnN6_Y", "store": "Rest. Terraza Portobelo", "openShiftPerWeek": 5, "schedule": [{"monday": [1, 1], "tuesday": [0, 0], "wednesday": [0, 1], "thursday": [0, 1], "friday": [0, 1]}]}, {"storeId": "ChIJAUO-FP6lBY8RdLX7uZAfrrU", "store": "Bisi", "openShiftPerWeek": 5, "schedule": [{"monday": [0, 0], "tuesday": [0, 0], "wednesday": [1, 0], "thursday": [1, 1], "friday": [1, 1]}]}, {"storeId": "ChIJKeLSqgemBY8RzM1AvMzc_ZY", "store": "The Islander", "openShiftPerWeek": 5, "schedule": [{"monday": [0, 1], "tuesday": [0, 0], "wednesday": [1, 1], "thursday": [0, 1], "friday": [0, 1]}]}, {"storeId": "ChIJ3fFElP-lBY8R9WUnepzxaC4", "store": "Trattoria Mr. Panino", "openShiftPerWeek": 2, "schedule": [{"monday": [0, 0], "tuesday": [0, 0], "wednesday": [0, 0], "thursday": [0, 0], "friday": [1, 1]}]}, {"storeId": "ChIJa76TsQCmBY8R5SoE4W9s8ws", "store": "Model Adventist College", "openShiftPerWeek": 5, "schedule": [{"monday": [0, 0], "tuesday": [1, 0], "wednesday": [1, 0], "thursday": [1, 0], "friday": [1, 1]}]}, {"storeId": "ChIJqTAkuVWvBY8RVxW9BrEG-bg", "store": "Caribe Azul Centro de Buceo", "openShiftPerWeek": 3, "schedule": [{"monday": [0, 1], "tuesday": [0, 1], "wednesday": [0, 0], "thursday": [0, 0], "friday": [1, 0]}]}, {"storeId": "ChIJQ22fZNKlBY8RBCunEJVEkUM", "store": "Infotep", "openShiftPerWeek": 7, "schedule": [{"monday": [0, 0], "tuesday": [1, 1], "wednesday": [1, 1], "thursday": [1, 1], "friday": [1, 0]}]}, {"storeId": "ChIJaWv6-f2lBY8R4gPOP-efr4k", "store": "Estacion de Policia San Andres", "openShiftPerWeek": 3, "schedule": [{"monday": [1, 0], "tuesday": [0, 0], "wednesday": [0, 1], "thursday": [1, 0], "friday": [0, 0]}]}, {"storeId": "ChIJmSZNyOKlBY8Rk9sJoVrPQb8", "store": "cdi sea colors", "openShiftPerWeek": 3, "schedule": [{"monday": [0, 0], "tuesday": [0, 1], "wednesday": [0, 0], "thursday": [0, 1], "friday": [1, 0]}]}, {"storeId": "ChIJ_Qn3dtGlBY8RkoqBNmfTNko", "store": "San Andr\u00e9s DHL CENTRO", "openShiftPerWeek": 7, "schedule": [{"monday": [0, 0], "tuesday": [0, 1], "wednesday": [1, 1], "thursday": [1, 1], "friday": [1, 1]}]}, {"storeId": "ChIJlWTYLAimBY8Rc1kd1pfH2j8", "store": "School House", "openShiftPerWeek": 6, "schedule": [{"monday": [1, 1], "tuesday": [1, 1], "wednesday": [0, 0], "thursday": [1, 0], "friday": [1, 0]}]}, {"storeId": "ChIJZS78Ug-mBY8RQeM_6Sv3mHs", "store": "Calegio El Esfuerzo", "openShiftPerWeek": 4, "schedule": [{"monday": [0, 1], "tuesday": [1, 0], "wednesday": [0, 1], "thursday": [1, 0], "friday": [0, 0]}]}, {"storeId": "ChIJ6avGbb2nBY8RWI1488-1bGg", "store": "SCALL SAN ANDR\u00c9S", "openShiftPerWeek": 5, "schedule": [{"monday": [1, 0], "tuesday": [0, 1], "wednesday": [1, 0], "thursday": [0, 1], "friday": [0, 1]}]}, {"storeId": "ChIJbVaDav6lBY8RgAYfUMrsIoQ", "store": "Costa Brava swimwear", "openShiftPerWeek": 5, "schedule": [{"monday": [0, 0], "tuesday": [0, 1], "wednesday": [0, 1], "thursday": [0, 1], "friday": [1, 1]}]}, {"storeId": "ChIJC5gzzP-lBY8RPTFWHTTqW3E", "store": "Madrid Shoes", "openShiftPerWeek": 2, "schedule": [{"monday": [0, 0], "tuesday": [1, 1], "wednesday": [0, 0], "thursday": [0, 0], "friday": [0, 0]}]}, {"storeId": "ChIJM3WWcv6lBY8R82d37qG0GTU", "store": "Gasolina Extra", "openShiftPerWeek": 4, "schedule": [{"monday": [0, 1], "tuesday": [0, 0], "wednesday": [1, 0], "thursday": [1, 0], "friday": [0, 1]}]}, {"storeId": "ChIJ8xJ_bP6lBY8RMqEcorlF5Q4", "store": "Almac\u00e9n Ch\u00e9vere,", "openShiftPerWeek": 7, "schedule": [{"monday": [1, 1], "tuesday": [0, 1], "wednesday": [1, 1], "thursday": [0, 1], "friday": [1, 0]}]}, {"storeId": "ChIJqbSH3P-lBY8RFUcu2SvWJ7E", "store": "Aiwa International Center", "openShiftPerWeek": 2, "schedule": [{"monday": [0, 0], "tuesday": [0, 1], "wednesday": [1, 0], "thursday": [0, 0], "friday": [0, 0]}]}, {"storeId": "ChIJuUseGY2lBY8RSYiXc6dUjZg", "store": "La Rivera", "openShiftPerWeek": 8, "schedule": [{"monday": [1, 1], "tuesday": [1, 1], "wednesday": [0, 1], "thursday": [1, 1], "friday": [1, 0]}]}, {"storeId": "ChIJRYNLdAalBY8RPn4U9BjU8Ig", "store": "Auriculares", "openShiftPerWeek": 7, "schedule": [{"monday": [0, 1], "tuesday": [1, 0], "wednesday": [0, 1], "thursday": [1, 1], "friday": [1, 1]}]}, {"storeId": "ChIJkz4QAGWlBY8R7oz3HdWyihE", "store": "Store JR Importados", "openShiftPerWeek": 3, "schedule": [{"monday": [1, 0], "tuesday": [0, 1], "wednesday": [1, 0], "thursday": [0, 0], "friday": [0, 0]}]}, {"storeId": "ChIJIYg_Sv6lBY8R7XbXJaAw5ss", "store": "Mini Max", "openShiftPerWeek": 9, "schedule": [{"monday": [1, 0], "tuesday": [1, 1], "wednesday": [1, 1], "thursday": [1, 1], "friday": [1, 1]}]}, {"storeId": "ChIJ7fmlNv6lBY8R9zLli631YXk", "store": "Zona Fit", "openShiftPerWeek": 3, "schedule": [{"monday": [1, 1], "tuesday": [0, 0], "wednesday": [0, 1], "thursday": [0, 0], "friday": [0, 0]}]}, {"storeId": "ChIJKVoNRv6lBY8RTTnenEL0VSI", "store": "Comercial Jacobo", "openShiftPerWeek": 4, "schedule": [{"monday": [0, 0], "tuesday": [1, 0], "wednesday": [1, 1], "thursday": [1, 0], "friday": [0, 0]}]}, {"storeId": "ChIJOZ_xeACmBY8RXlfzQ5ola0o", "store": "Malib Plaza", "openShiftPerWeek": 4, "schedule": [{"monday": [0, 0], "tuesday": [1, 0], "wednesday": [1, 1], "thursday": [0, 0], "friday": [0, 1]}]}, {"storeId": "ChIJk9gSstClBY8R1b09A1dzhn4", "store": "Lili Pink", "openShiftPerWeek": 5, "schedule": [{"monday": [1, 1], "tuesday": [0, 0], "wednesday": [0, 0], "thursday": [1, 1], "friday": [0, 1]}]}, {"storeId": "ChIJGyxpLsGlBY8RFjHVZRIJpdw", "store": "Centro Comercial Unisanandr\u00e9s", "openShiftPerWeek": 5, "schedule": [{"monday": [0, 0], "tuesday": [1, 1], "wednesday": [0, 0], "thursday": [0, 1], "friday": [1, 1]}]}, {"storeId": "ChIJq5ydOf6lBY8RhbZQB0kgxPE", "store": "LOCAL CELULARES", "openShiftPerWeek": 4, "schedule": [{"monday": [0, 1], "tuesday": [0, 1], "wednesday": [1, 0], "thursday": [1, 0], "friday": [0, 0]}]}, {"storeId": "ChIJqTxngQCmBY8RrECBYDi8uxo", "store": "Mega Outlet", "openShiftPerWeek": 7, "schedule": [{"monday": [0, 1], "tuesday": [1, 1], "wednesday": [0, 1], "thursday": [1, 1], "friday": [1, 0]}]}, {"storeId": "ChIJEZV2gwCmBY8RUwh-IpdOHaQ", "store": "Ranpi's", "openShiftPerWeek": 7, "schedule": [{"monday": [0, 1], "tuesday": [1, 1], "wednesday": [1, 0], "thursday": [1, 1], "friday": [0, 1]}]}, {"storeId": "ChIJvcXMH_6lBY8RayNxdmVNKM0", "store": "Almacen Super descuentos L y D", "openShiftPerWeek": 8, "schedule": [{"monday": [1, 1], "tuesday": [1, 1], "wednesday": [1, 1], "thursday": [0, 0], "friday": [1, 1]}]}, {"storeId": "ChIJD9svbgemBY8R6Fh2vgkLLyE", "store": "Tour", "openShiftPerWeek": 4, "schedule": [{"monday": [0, 1], "tuesday": [0, 1], "wednesday": [0, 1], "thursday": [0, 1], "friday": [0, 0]}]}, {"storeId": "ChIJu1oZLgimBY8R3fLR9nnzVcE", "store": "San Andres Island center", "openShiftPerWeek": 7, "schedule": [{"monday": [0, 0], "tuesday": [1, 1], "wednesday": [1, 1], "thursday": [1, 1], "friday": [0, 1]}]}, {"storeId": "ChIJ37XLlf-lBY8RcaRxF1mYRRU", "store": "Fish Spa Island", "openShiftPerWeek": 5, "schedule": [{"monday": [1, 0], "tuesday": [0, 0], "wednesday": [1, 1], "thursday": [1, 1], "friday": [0, 0]}]}, {"storeId": "ChIJicXegf2lBY8RIntttp5KHtI", "store": "Estadio De Softbol", "openShiftPerWeek": 8, "schedule": [{"monday": [1, 0], "tuesday": [1, 1], "wednesday": [1, 1], "thursday": [1, 1], "friday": [1, 0]}]}, {"storeId": "ChIJ_XfJL_KlBY8R8cvV0yENxK4", "store": "summerland", "openShiftPerWeek": 3, "schedule": [{"monday": [1, 1], "tuesday": [0, 0], "wednesday": [1, 0], "thursday": [0, 0], "friday": [0, 0]}]}, {"storeId": "ChIJ3dLY4_-lBY8R1wWKNGiXXKY", "store": "Quicksilver", "openShiftPerWeek": 6, "schedule": [{"monday": [1, 1], "tuesday": [1, 1], "wednesday": [0, 0], "thursday": [1, 0], "friday": [1, 0]}]}, {"storeId": "ChIJCWg74IClBY8RbHPp24LppgA", "store": "Summerland Store", "openShiftPerWeek": 2, "schedule": [{"monday": [0, 0], "tuesday": [0, 1], "wednesday": [0, 0], "thursday": [0, 1], "friday": [0, 0]}]}, {"storeId": "ChIJ9RWrv-ulBY8RRVQ-2Vh7-Kk", "store": "Inversiones Y Negocios El Mana S.A.S.", "openShiftPerWeek": 4, "schedule": [{"monday": [0, 0], "tuesday": [1, 1], "wednesday": [0, 0], "thursday": [0, 1], "friday": [0, 1]}]}, {"storeId": "ChIJo9D7z_-lBY8Rc35IVZAEsWI", "store": "Productos de Belleza | Perfumes, Maquillaje y Cosm\u00e9ticos | House Of Beauty San Andr\u00e9s", "openShiftPerWeek": 3, "schedule": [{"monday": [0, 1], "tuesday": [0, 0], "wednesday": [0, 0], "thursday": [1, 0], "friday": [0, 1]}]}, {"storeId": "ChIJNf-HzP-lBY8R28z3kCncu1A", "store": "LE SOLAR PRONTA", "openShiftPerWeek": 5, "schedule": [{"monday": [1, 0], "tuesday": [1, 0], "wednesday": [1, 0], "thursday": [1, 0], "friday": [0, 1]}]}, {"storeId": "ChIJLyyyy_-lBY8R2H8X8pBm6Ds", "store": "Supermercado Superplaya", "openShiftPerWeek": 10, "schedule": [{"monday": [1, 1], "tuesday": [1, 1], "wednesday": [1, 1], "thursday": [1, 1], "friday": [1, 1]}]}, {"storeId": "ChIJNRfGmBOlBY8RtwEOahrnaog", "store": "GlobCom Delivey Market", "openShiftPerWeek": 10, "schedule": [{"monday": [1, 1], "tuesday": [1, 1], "wednesday": [1, 1], "thursday": [1, 1], "friday": [1, 1]}]}, {"storeId": "ChIJ69XOGP6lBY8RmdxSaD-iyrs", "store": "Coco Sweey (favorable)", "openShiftPerWeek": 10, "schedule": [{"monday": [1, 1], "tuesday": [1, 1], "wednesday": [1, 1], "thursday": [1, 1], "friday": [1, 1]}]}, {"storeId": "ChIJhaKWCv6lBY8RDlNb9G1Zffc", "store": "Surtimat", "openShiftPerWeek": 10, "schedule": [{"monday": [1, 1], "tuesday": [1, 1], "wednesday": [1, 1], "thursday": [1, 1], "friday": [1, 1]}]}, {"storeId": "ChIJfa0_kf2lBY8RsbbpW5Kdk6o", "store": "Surtimar", "openShiftPerWeek": 10, "schedule": [{"monday": [1, 1], "tuesday": [1, 1], "wednesday": [1, 1], "thursday": [1, 1], "friday": [1, 1]}]}, {"storeId": "ChIJB2W0l6alBY8R3XgFd5UTTSo", "store": "Minimarket inda house", "openShiftPerWeek": 10, "schedule": [{"monday": [1, 1], "tuesday": [1, 1], "wednesday": [1, 1], "thursday": [1, 1], "friday": [1, 1]}]}, {"storeId": "ChIJqxHUEBelBY8RIYfF_DOniKM", "store": "Distribuidora Silemar & La Victoria", "openShiftPerWeek": 10, "schedule": [{"monday": [1, 1], "tuesday": [1, 1], "wednesday": [1, 1], "thursday": [1, 1], "friday": [1, 1]}]}, {"storeId": "ChIJF8ZuJ_6lBY8R8NBns_ydlfo", "store": "Unisanandres Mall", "openShiftPerWeek": 6, "schedule": [{"monday": [0, 1], "tuesday": [0, 1], "wednesday": [1, 0], "thursday": [1, 0], "friday": [1, 1]}]}, {"storeId": "ChIJP0-CggCmBY8R-m2fkih-Bpg", "store": "On Vacation Caribbean All Inclusive", "openShiftPerWeek": 7, "schedule": [{"monday": [1, 0], "tuesday": [1, 1], "wednesday": [1, 0], "thursday": [1, 1], "friday": [1, 0]}]}, {"storeId": "ChIJleTnlyulBY8RdK1YxMufJas", "store": "seaflower adventure", "openShiftPerWeek": 4, "schedule": [{"monday": [0, 1], "tuesday": [0, 0], "wednesday": [0, 1], "thursday": [1, 0], "friday": [0, 1]}]}, {"storeId": "ChIJ_32ayQCmBY8RGKzbNkegtD8", "store": "Main Beach (Tourist) San Andres Island", "openShiftPerWeek": 5, "schedule": [{"monday": [0, 1], "tuesday": [0, 0], "wednesday": [0, 1], "thursday": [1, 1], "friday": [1, 0]}]}, {"storeId": "ChIJD6qbaQamBY8Rs67szzfrvGQ", "store": "I Love San Andr\u00e9s", "openShiftPerWeek": 3, "schedule": [{"monday": [0, 0], "tuesday": [0, 0], "wednesday": [1, 0], "thursday": [1, 0], "friday": [0, 1]}]}, {"storeId": "ChIJj2PouQCmBY8R424M_o6WoL8", "store": "Viajes Portofino", "openShiftPerWeek": 6, "schedule": [{"monday": [1, 1], "tuesday": [0, 0], "wednesday": [0, 1], "thursday": [1, 0], "friday": [1, 1]}]}, {"storeId": "ChIJP_kOtv-lBY8RLq-rDXmxmfQ", "store": "Viajes y Turismo", "openShiftPerWeek": 2, "schedule": [{"monday": [0, 0], "tuesday": [0, 0], "wednesday": [0, 1], "thursday": [0, 0], "friday": [0, 1]}]}, {"storeId": "ChIJf5qsg_WlBY8RFvd1cJKnICo", "store": "Nissi Vip Travel and Tours", "openShiftPerWeek": 1, "schedule": [{"monday": [0, 0], "tuesday": [0, 0], "wednesday": [1, 0], "thursday": [0, 0], "friday": [0, 0]}]}]